{
  "project_info": {
    "project_number": "1062985984144",
    "project_id": "braintera-53d60",
    "storage_bucket": "braintera-53d60.firebasestorage.app"
  },
  "client": [
    {
      "client_info": {
        "mobilesdk_app_id": "1:1062985984144:android:f49dc9daa89bec3af3d015",
        "android_client_info": {
          "package_name": "com.microdose.ball"
        }
      },
      "oauth_client": [],
      "api_key": [
        {
          "current_key": "AIzaSyCNWTDQfxv5b_9I-SkWrdJ54y5yOiaFVd4"
        }
      ],
      "services": {
        "appinvite_service": {
          "other_platform_oauth_client": []
        }
      }
    }
  ],
  "configuration_version": "1"
}
